tracing/__init__.py
tracing/admin.py
tracing/apps.py
tracing/middleware.py
tracing/models.py
tracing/services.py
tracing/signals.py
tracing/tests.py
tracing/migrations/0001_initial.py
tracing/migrations/0002_auto_20210628_1608.py
tracing/migrations/0003_auto_20210707_2033.py
tracing/migrations/0004_auto_20210910_0906.py
tracing/migrations/__init__.py
gmcm_django_tracing-2.0.2.dist-info/LICENCE
gmcm_django_tracing-2.0.2.dist-info/METADATA
gmcm_django_tracing-2.0.2.dist-info/WHEEL
gmcm_django_tracing-2.0.2.dist-info/top_level.txt
gmcm_django_tracing-2.0.2.dist-info/RECORD
